ibbyphonevalidator/__init__.py
ibbyphonevalidator/validator.py
ibbyphonevalidator-0.2.1.dist-info/METADATA
ibbyphonevalidator-0.2.1.dist-info/WHEEL
ibbyphonevalidator-0.2.1.dist-info/RECORD
