Metadata-Version: 2.1
Name: ibbyphonevalidator
Version: 0.2.1
Summary: More documentation to come 😊
Author: ibrahimsaidi
Author-email: ibrahim.aka.ajax@gmail.com
Requires-Python: >=3.12,<4.0
Classifier: Programming Language :: Python :: 3
Requires-Dist: requests (>=2.31.0,<3.0.0)
